{
  "swagger": "2.0",
  "info": {
    "title": "寵知 API",
    "version": "1.0.0",
    "description": "API 文件"
  },
  "host": "localhost:8000",
  "basePath": "/",
  "schemes": [
    "http",
    "https"
  ],
  "securityDefinitions": {
    "apiKeyAuth": {
      "type": "apiKey",
      "in": "headers",
      "name": "authorization",
      "description": "請加上 API Token"
    }
  },
  "paths": {
    "/v1/register": {
      "post": {
        "tags": [
          "登入系統 API"
        ],
        "description": "註冊帳號",
        "parameters": [
          {
            "name": "body",
            "description": "資料格式",
            "in": "body",
            "required": true,
            "schema": {
              "type": "object",
              "properties": {
                "name": {
                  "type": "string",
                  "example": "Benson"
                },
                "email": {
                  "type": "string",
                  "example": "AbcTest@gmail.com"
                },
                "password": {
                  "type": "string",
                  "example": "Abc123#"
                }
              }
            }
          }
        ],
        "responses": {
          "200": {
            "description": "成功",
            "schema": {
              "type": "object",
              "properties": {
                "success": {
                  "type": "boolean",
                  "example": true
                },
                "statusCode": {
                  "type": "number",
                  "example": 200
                },
                "message": {
                  "type": "string",
                  "example": "Success"
                },
                "data": {
                  "type": "object",
                  "properties": {
                    "name": {
                      "type": "string",
                      "example": "Benson"
                    },
                    "email": {
                      "type": "string",
                      "example": "testfge2@gmail.com"
                    },
                    "__v": {
                      "type": "number",
                      "example": 0
                    }
                  }
                }
              },
              "xml": {
                "name": "main"
              }
            }
          },
          "400": {
            "success": false,
            "statusCode": 400,
            "message": "Failure",
            "description": "Bad Request"
          },
          "500": {
            "description": "伺服器發生錯誤",
            "schema": {
              "type": "object",
              "properties": {
                "statusCode": {
                  "type": "number",
                  "example": 500
                },
                "isSuccess": {
                  "type": "boolean",
                  "example": false
                },
                "message": {
                  "type": "string",
                  "example": "System error, please contact the system administrator"
                }
              },
              "xml": {
                "name": "main"
              }
            }
          }
        }
      }
    },
    "/v1/login": {
      "post": {
        "tags": [
          "登入系統 API"
        ],
        "description": "註冊帳號",
        "parameters": [
          {
            "name": "body",
            "description": "資料格式",
            "in": "body",
            "required": true,
            "schema": {
              "type": "object",
              "properties": {
                "email": {
                  "type": "string",
                  "example": "AbcTest@gmail.com"
                },
                "password": {
                  "type": "string",
                  "example": "Abc123#"
                }
              }
            }
          }
        ],
        "responses": {
          "200": {
            "description": "成功",
            "schema": {
              "type": "object",
              "properties": {
                "success": {
                  "type": "boolean",
                  "example": true
                },
                "statusCode": {
                  "type": "number",
                  "example": 200
                },
                "message": {
                  "type": "string",
                  "example": "Success"
                },
                "data": {
                  "type": "object",
                  "properties": {
                    "name": {
                      "type": "string",
                      "example": "Benson"
                    },
                    "email": {
                      "type": "string",
                      "example": "AbcTest@gmail.com"
                    },
                    "__v": {
                      "type": "number",
                      "example": 0
                    },
                    "token": {
                      "type": "string",
                      "example": "eyJhbGciOiJIUzI1NiIsInR5cCI6IkpXVCJ9.eyJfaWQiOiI2NDZkOGJmODVmNTJhZTk2ODFiODg1OTMiLCJpYXQiOjE2ODQ5MDA5MDR9.4_l8XUaVPW58-6VCpt51-QkLq5SyKRnYndt1P_xQ2Ng"
                    }
                  }
                }
              },
              "xml": {
                "name": "main"
              }
            }
          },
          "400": {
            "description": "錯誤的請求",
            "schema": {
              "type": "object",
              "properties": {
                "success": {
                  "type": "boolean",
                  "example": false
                },
                "statusCode": {
                  "type": "number",
                  "example": 400
                },
                "message": {
                  "type": "string",
                  "example": "Invalid credentials"
                },
                "data": {
                  "type": "object",
                  "properties": {
                    "email": {
                      "type": "string",
                      "example": "AbcTest@gmail.com"
                    }
                  }
                }
              },
              "xml": {
                "name": "main"
              }
            }
          },
          "404": {
            "description": "Not Found"
          },
          "500": {
            "description": "伺服器發生錯誤",
            "schema": {
              "type": "object",
              "properties": {
                "statusCode": {
                  "type": "number",
                  "example": 500
                },
                "isSuccess": {
                  "type": "boolean",
                  "example": false
                },
                "message": {
                  "type": "string",
                  "example": "System error, please contact the system administrator"
                }
              },
              "xml": {
                "name": "main"
              }
            }
          }
        }
      }
    },
    "/v1/user/show": {
      "get": {
        "tags": [
          "登入系統 API"
        ],
        "description": "註冊帳號",
        "parameters": [],
        "responses": {
          "200": {
            "description": "成功",
            "schema": {
              "type": "object",
              "properties": {
                "success": {
                  "type": "boolean",
                  "example": true
                },
                "statusCode": {
                  "type": "number",
                  "example": 200
                },
                "message": {
                  "type": "string",
                  "example": "Success"
                },
                "data": {
                  "type": "object",
                  "properties": {
                    "_id": {
                      "type": "string",
                      "example": "646d8bf85f52ae9681b88593"
                    },
                    "name": {
                      "type": "string",
                      "example": "Benson"
                    },
                    "email": {
                      "type": "string",
                      "example": "Abc123#@gmail.com"
                    },
                    "password": {
                      "type": "string",
                      "example": "$2a$10$1yR.UPzTukYyVdiLUTHvhugqp1nBEjZmKD31inX2XGlLpUIGvAwly"
                    },
                    "__v": {
                      "type": "number",
                      "example": 0
                    }
                  }
                }
              },
              "xml": {
                "name": "main"
              }
            }
          },
          "400": {
            "description": "錯誤的請求",
            "schema": {
              "type": "object",
              "properties": {
                "success": {
                  "type": "boolean",
                  "example": false
                },
                "statusCode": {
                  "type": "number",
                  "example": 400
                },
                "message": {
                  "type": "string",
                  "example": "Unauthenticated or user not found"
                }
              },
              "xml": {
                "name": "main"
              }
            }
          },
          "500": {
            "description": "伺服器發生錯誤",
            "schema": {
              "type": "object",
              "properties": {
                "statusCode": {
                  "type": "number",
                  "example": 500
                },
                "isSuccess": {
                  "type": "boolean",
                  "example": false
                },
                "message": {
                  "type": "string",
                  "example": "System error, please contact the system administrator"
                }
              },
              "xml": {
                "name": "main"
              }
            }
          }
        },
        "security": [
          {
            "apiKeyAuth": []
          }
        ]
      }
    },
    "/v1/user/update": {
      "put": {
        "tags": [
          "登入系統 API"
        ],
        "description": "註冊帳號",
        "parameters": [
          {
            "name": "body",
            "description": "資料格式",
            "in": "body",
            "required": true,
            "schema": {
              "type": "object",
              "properties": {
                "name": {
                  "type": "string",
                  "example": "patrick"
                },
                "bio": {
                  "type": "string",
                  "example": "Just another software developer"
                },
                "nickname": {
                  "type": "string",
                  "example": "pat"
                }
              }
            }
          }
        ],
        "responses": {
          "200": {
            "description": "成功",
            "schema": {
              "type": "object",
              "properties": {
                "success": {
                  "type": "boolean",
                  "example": true
                },
                "statusCode": {
                  "type": "number",
                  "example": 200
                },
                "message": {
                  "type": "string",
                  "example": "Success"
                },
                "data": {
                  "type": "object",
                  "properties": {
                    "_id": {
                      "type": "string",
                      "example": "646d8bf85f52ae9681b88593"
                    },
                    "name": {
                      "type": "string",
                      "example": "Benson"
                    },
                    "email": {
                      "type": "string",
                      "example": "Abc123#@gmail.com"
                    },
                    "password": {
                      "type": "string",
                      "example": "$2a$10$1yR.UPzTukYyVdiLUTHvhugqp1nBEjZmKD31inX2XGlLpUIGvAwly"
                    },
                    "__v": {
                      "type": "number",
                      "example": 0
                    }
                  }
                }
              },
              "xml": {
                "name": "main"
              }
            }
          },
          "400": {
            "description": "錯誤的請求",
            "schema": {
              "type": "object",
              "properties": {
                "success": {
                  "type": "boolean",
                  "example": false
                },
                "statusCode": {
                  "type": "number",
                  "example": 400
                },
                "message": {
                  "type": "string",
                  "example": "Unauthenticated or user not found"
                }
              },
              "xml": {
                "name": "main"
              }
            }
          },
          "500": {
            "description": "伺服器發生錯誤",
            "schema": {
              "type": "object",
              "properties": {
                "statusCode": {
                  "type": "number",
                  "example": 500
                },
                "isSuccess": {
                  "type": "boolean",
                  "example": false
                },
                "message": {
                  "type": "string",
                  "example": "System error, please contact the system administrator"
                }
              },
              "xml": {
                "name": "main"
              }
            }
          }
        },
        "security": [
          {
            "apiKeyAuth": []
          }
        ]
      }
    },
    "/v1/logout": {
      "post": {
        "description": "",
        "parameters": [],
        "responses": {
          "200": {
            "description": "OK"
          }
        }
      }
    },
    "/v1/": {
      "get": {
        "description": "",
        "parameters": [],
        "responses": {
          "200": {
            "description": "OK"
          }
        }
      },
      "post": {
        "description": "",
        "parameters": [
          {
            "name": "body",
            "in": "body",
            "schema": {
              "type": "object",
              "properties": {
                "username": {
                  "example": "any"
                },
                "password": {
                  "example": "any"
                }
              }
            }
          }
        ],
        "responses": {
          "200": {
            "description": "OK"
          },
          "404": {
            "description": "Not Found"
          }
        }
      }
    },
    "/v1/fakeInformation/getAllUserId": {
      "get": {
        "tags": [
          "FakeInformation - 假資料 API"
        ],
        "description": "取得全部使用者的 _id 資料",
        "parameters": [],
        "responses": {
          "200": {
            "description": "成功",
            "schema": {
              "type": "object",
              "properties": {
                "statusCode": {
                  "type": "number",
                  "example": 200
                },
                "isSuccess": {
                  "type": "boolean",
                  "example": true
                },
                "message": {
                  "type": "string",
                  "example": "Success"
                },
                "data": {
                  "type": "array",
                  "example": [
                    "6462f6e51d25094b3e5b94ca"
                  ],
                  "items": {
                    "type": "string"
                  }
                }
              },
              "xml": {
                "name": "main"
              }
            }
          },
          "400": {
            "description": "錯誤的請求",
            "schema": {
              "type": "object",
              "properties": {
                "statusCode": {
                  "type": "number",
                  "example": 400
                },
                "isSuccess": {
                  "type": "boolean",
                  "example": false
                },
                "message": {
                  "type": "string",
                  "example": "Failure"
                }
              },
              "xml": {
                "name": "main"
              }
            }
          },
          "500": {
            "description": "伺服器發生錯誤",
            "schema": {
              "type": "object",
              "properties": {
                "statusCode": {
                  "type": "number",
                  "example": 500
                },
                "isSuccess": {
                  "type": "boolean",
                  "example": false
                },
                "message": {
                  "type": "string",
                  "example": "System error, please contact the system administrator"
                }
              },
              "xml": {
                "name": "main"
              }
            }
          }
        }
      }
    },
    "/v1/fakeInformation/getAllCourseHierarchys": {
      "get": {
        "tags": [
          "FakeInformation - 假資料 API"
        ],
        "description": "取得全部課程彙總資料",
        "parameters": [],
        "responses": {
          "200": {
            "description": "成功",
            "schema": {
              "type": "object",
              "properties": {
                "statusCode": {
                  "type": "number",
                  "example": 200
                },
                "isSuccess": {
                  "type": "boolean",
                  "example": true
                },
                "message": {
                  "type": "string",
                  "example": "Success"
                },
                "data": {
                  "type": "array",
                  "items": {
                    "type": "object",
                    "properties": {
                      "_id": {
                        "type": "string",
                        "example": "646f7e2f4802a2dbf6b3eb83"
                      },
                      "user": {
                        "type": "string",
                        "example": "646b7386c4f79ea9d11ff6e7"
                      },
                      "tagNames": {
                        "type": "array",
                        "example": [
                          "狗狗訓練"
                        ],
                        "items": {
                          "type": "string"
                        }
                      },
                      "cover": {
                        "type": "string",
                        "example": "z/dog-golden-retriever-jumping-autumn-leaves-autumnal-sunlight-77861618.jpg"
                      },
                      "promoVideo": {},
                      "title": {
                        "type": "string",
                        "example": "狗狗訓練入門課程"
                      },
                      "shortDescription": {
                        "type": "string",
                        "example": "<p>尿布訓練是狗狗的基礎訓練之一，它可以幫助您的狗狗建立適當的排泄習慣。</p>\n<ul>\n <li>選擇適合的尿布訓練方法：包括使用尿布墊片、尿布盆等不同方式。</li>\n <li>建立排泄地點：訓練狗狗在指定的區域內進行排泄。</li>\n <li>正確回饋和糾正方法：適時給予獎勵和糾正以加強尿布訓練效果。</li>\n</ul>\n<p>透過尿布訓練，您的狗狗將學會在指定的地點排泄，減少室內意外，並建立良好的衛生習慣。</p>"
                      },
                      "description": {
                        "type": "string",
                        "example": "這堂課將教您如何選擇適合的狗糧，並提供營養均衡的飲食建議。我們將討論飲食需求、餵食時間和食物選擇，確保您的狗狗獲得健康的營養。"
                      },
                      "level": {
                        "type": "number",
                        "example": 1
                      },
                      "price": {
                        "type": "number",
                        "example": 3148
                      },
                      "enrollmentCount": {
                        "type": "number",
                        "example": 8152
                      },
                      "totalTime": {
                        "type": "number",
                        "example": 488188
                      },
                      "totalNumber": {
                        "type": "number",
                        "example": 53
                      },
                      "isFree": {
                        "type": "boolean",
                        "example": false
                      },
                      "isPopular": {
                        "type": "boolean",
                        "example": true
                      },
                      "isPublished": {
                        "type": "boolean",
                        "example": true
                      },
                      "discountDate": {},
                      "shelfDate": {
                        "type": "string",
                        "example": "2023-05-27T03:18:13.292Z"
                      },
                      "createdAt": {
                        "type": "string",
                        "example": "2022-01-14T01:16:25.892Z"
                      },
                      "updatedAt": {
                        "type": "string",
                        "example": "2023-01-26T09:36:33.068Z"
                      },
                      "chapters": {
                        "type": "array",
                        "items": {
                          "type": "object",
                          "properties": {
                            "_id": {
                              "type": "string",
                              "example": "A00004"
                            },
                            "sequence": {
                              "type": "number",
                              "example": 5
                            },
                            "title": {
                              "type": "string",
                              "example": "進階技巧"
                            },
                            "totalTime": {
                              "type": "number",
                              "example": 467105
                            },
                            "totalNumber": {
                              "type": "number",
                              "example": 30
                            },
                            "subchapters": {
                              "type": "array",
                              "items": {
                                "type": "object",
                                "properties": {
                                  "_id": {
                                    "type": "string",
                                    "example": "A000042"
                                  },
                                  "sequence": {
                                    "type": "number",
                                    "example": 3
                                  },
                                  "title": {
                                    "type": "string",
                                    "example": "尋找物品指令"
                                  },
                                  "content": {},
                                  "fileName": {
                                    "type": "string",
                                    "example": "192191?h=be09c77984&app_id=122963"
                                  },
                                  "fileType": {
                                    "type": "number",
                                    "example": 0
                                  },
                                  "time": {
                                    "type": "number",
                                    "example": 342810
                                  }
                                }
                              }
                            }
                          }
                        }
                      }
                    }
                  }
                }
              },
              "xml": {
                "name": "main"
              }
            }
          },
          "400": {
            "description": "錯誤的請求",
            "schema": {
              "type": "object",
              "properties": {
                "statusCode": {
                  "type": "number",
                  "example": 400
                },
                "isSuccess": {
                  "type": "boolean",
                  "example": false
                },
                "message": {
                  "type": "string",
                  "example": "Failure"
                }
              },
              "xml": {
                "name": "main"
              }
            }
          },
          "500": {
            "description": "伺服器發生錯誤",
            "schema": {
              "type": "object",
              "properties": {
                "statusCode": {
                  "type": "number",
                  "example": 500
                },
                "isSuccess": {
                  "type": "boolean",
                  "example": false
                },
                "message": {
                  "type": "string",
                  "example": "System error, please contact the system administrator"
                }
              },
              "xml": {
                "name": "main"
              }
            }
          }
        }
      }
    },
    "/v1/fakeInformation/getAllCoupons": {
      "get": {
        "tags": [
          "FakeInformation - 假資料 API"
        ],
        "description": "取得全部標籤資料",
        "parameters": [],
        "responses": {
          "200": {
            "description": "成功",
            "schema": {
              "type": "object",
              "properties": {
                "statusCode": {
                  "type": "number",
                  "example": 200
                },
                "isSuccess": {
                  "type": "boolean",
                  "example": true
                },
                "message": {
                  "type": "string",
                  "example": "Success"
                },
                "data": {
                  "type": "array",
                  "items": {
                    "type": "object",
                    "properties": {
                      "_id": {
                        "type": "string",
                        "example": "646d8478f3bdeca0cd4c4558"
                      },
                      "tagNames": {
                        "type": "array",
                        "example": [
                          "貓咪食譜",
                          "寵物健康照護",
                          "貓咪的解悶遊戲"
                        ],
                        "items": {
                          "type": "string"
                        }
                      },
                      "couponCode": {
                        "type": "string",
                        "example": "jPO0UZ8A"
                      },
                      "discountPrice": {
                        "type": "number",
                        "example": 665
                      },
                      "isEnabled": {
                        "type": "boolean",
                        "example": true
                      },
                      "startDate": {
                        "type": "string",
                        "example": "2023-03-16T06:16:34.664Z"
                      },
                      "endDate": {
                        "type": "string",
                        "example": "2023-06-30T15:19:27.333Z"
                      },
                      "createdAt": {
                        "type": "string",
                        "example": "2022-07-15T02:54:35.417Z"
                      },
                      "updatedAt": {
                        "type": "string",
                        "example": "2022-12-21T15:00:47.966Z"
                      }
                    }
                  }
                }
              },
              "xml": {
                "name": "main"
              }
            }
          },
          "400": {
            "description": "錯誤的請求",
            "schema": {
              "type": "object",
              "properties": {
                "statusCode": {
                  "type": "number",
                  "example": 400
                },
                "isSuccess": {
                  "type": "boolean",
                  "example": false
                },
                "message": {
                  "type": "string",
                  "example": "Failure"
                }
              },
              "xml": {
                "name": "main"
              }
            }
          },
          "500": {
            "description": "伺服器發生錯誤",
            "schema": {
              "type": "object",
              "properties": {
                "statusCode": {
                  "type": "number",
                  "example": 500
                },
                "isSuccess": {
                  "type": "boolean",
                  "example": false
                },
                "message": {
                  "type": "string",
                  "example": "System error, please contact the system administrator"
                }
              },
              "xml": {
                "name": "main"
              }
            }
          }
        }
      }
    },
    "/v1/fakeInformation/generateCourseHierarchysData": {
      "get": {
        "tags": [
          "FakeInformation - 假資料 API"
        ],
        "description": "產生假資料至課程彙總資料",
        "parameters": [],
        "responses": {
          "200": {
            "description": "成功",
            "schema": {
              "type": "object",
              "properties": {
                "statusCode": {
                  "type": "number",
                  "example": 200
                },
                "isSuccess": {
                  "type": "boolean",
                  "example": true
                },
                "message": {
                  "type": "string",
                  "example": "Success"
                }
              },
              "xml": {
                "name": "main"
              }
            }
          },
          "400": {
            "description": "錯誤的請求",
            "schema": {
              "type": "object",
              "properties": {
                "statusCode": {
                  "type": "number",
                  "example": 400
                },
                "isSuccess": {
                  "type": "boolean",
                  "example": false
                },
                "message": {
                  "type": "string",
                  "example": "Failure"
                }
              },
              "xml": {
                "name": "main"
              }
            }
          },
          "500": {
            "description": "伺服器發生錯誤",
            "schema": {
              "type": "object",
              "properties": {
                "statusCode": {
                  "type": "number",
                  "example": 500
                },
                "isSuccess": {
                  "type": "boolean",
                  "example": false
                },
                "message": {
                  "type": "string",
                  "example": "System error, please contact the system administrator"
                }
              },
              "xml": {
                "name": "main"
              }
            }
          }
        }
      }
    },
    "/v1/fakeInformation/generateCouponsData": {
      "get": {
        "tags": [
          "FakeInformation - 假資料 API"
        ],
        "description": "產生假資料至平台標籤資料表",
        "parameters": [],
        "responses": {
          "200": {
            "description": "成功",
            "schema": {
              "type": "object",
              "properties": {
                "statusCode": {
                  "type": "number",
                  "example": 200
                },
                "isSuccess": {
                  "type": "boolean",
                  "example": true
                },
                "message": {
                  "type": "string",
                  "example": "Success"
                }
              },
              "xml": {
                "name": "main"
              }
            }
          },
          "400": {
            "description": "錯誤的請求",
            "schema": {
              "type": "object",
              "properties": {
                "statusCode": {
                  "type": "number",
                  "example": 400
                },
                "isSuccess": {
                  "type": "boolean",
                  "example": false
                },
                "message": {
                  "type": "string",
                  "example": "Failure"
                }
              },
              "xml": {
                "name": "main"
              }
            }
          },
          "500": {
            "description": "伺服器發生錯誤",
            "schema": {
              "type": "object",
              "properties": {
                "statusCode": {
                  "type": "number",
                  "example": 500
                },
                "isSuccess": {
                  "type": "boolean",
                  "example": false
                },
                "message": {
                  "type": "string",
                  "example": "System error, please contact the system administrator"
                }
              },
              "xml": {
                "name": "main"
              }
            }
          }
        }
      }
    },
    "/v1/fakeInformation/createCourseHierarchys": {
      "post": {
        "tags": [
          "FakeInformation - 假資料 API"
        ],
        "description": "新增一筆課程彙總資料",
        "parameters": [
          {
            "name": "body",
            "description": "資料格式",
            "in": "body",
            "required": true,
            "schema": {
              "type": "object",
              "properties": {
                "user": {
                  "type": "string",
                  "example": "645a39c19ea91c0447216cc6"
                },
                "tagsNames": {
                  "type": "array",
                  "example": [
                    "貓咪食譜"
                  ],
                  "items": {
                    "type": "string"
                  }
                },
                "cover": {
                  "type": "string",
                  "example": "https://fastly.picsum.photos/id/249/200/300.jpg?hmac=HXJz3fKmXquFNHrfyd1yRHUYx9SheA_j2gbbya_4mlA"
                },
                "promoVideo": {
                  "type": "string",
                  "example": "https://example.com/videos/promo_video.mp4"
                },
                "title": {
                  "type": "string",
                  "example": "成為寵物訓練達人:寵物訓練入門基礎課程"
                },
                "shortDescription": {
                  "type": "string",
                  "example": "犬學堂於2009年成立，至今超過13年，絕對係香港最具規模、實力既狗狗酒店、樂園、訓練中心。我們主要提供狗隻訓練，並設有狗酒店、狗泳池、狗公園、狗餐廳等設施及服務。主要訓練課程：- 30日基本訓練寄宿課程- 45日高級訓練寄宿課程"
                },
                "description": {
                  "type": "string",
                  "example": "本課程適合對象 ：家有幼犬之飼主。您將能夠透過本課程獲得：基礎幼犬互動訓練提高幼犬社會化經驗提高幼犬於外界環境之適應力習得犬隻基礎馴養技巧幼犬性格尚未成長完全，正是適合進行各項訓練的年齡段！無論您是已有馴養經驗、亦或是初次飼養幼犬隻飼主，您都能夠透過本課程獲得基礎寵物訓練的知識與技巧。本課程將幫助您透過各項技巧提高犬隻社會化與性格穩定度 @src@src. 查看更多立即購課"
                },
                "level": {
                  "type": "number",
                  "example": 0
                },
                "price": {
                  "type": "number",
                  "example": 2500
                },
                "discountPrice": {
                  "type": "number",
                  "example": 1000
                },
                "enrollmentCount": {
                  "type": "number",
                  "example": 0
                },
                "totalTime": {
                  "type": "number",
                  "example": 43200
                },
                "totalNumber": {
                  "type": "number",
                  "example": 55
                },
                "is_free": {
                  "type": "boolean",
                  "example": false
                },
                "is_published": {
                  "type": "boolean",
                  "example": true
                },
                "discountDate": {
                  "type": "string",
                  "example": "2023/05/01"
                },
                "shelfDate": {
                  "type": "string",
                  "example": "2023/05/31"
                },
                "createdAt": {
                  "type": "string",
                  "example": "2023/01/01"
                },
                "updatedAt": {
                  "type": "string",
                  "example": "2023/05/08"
                },
                "chapters": {
                  "type": "array",
                  "items": {
                    "type": "object",
                    "properties": {
                      "_id": {
                        "type": "string",
                        "example": "6459b6cdaea0942f035f2e37-B001"
                      },
                      "sequence": {
                        "type": "number",
                        "example": 1
                      },
                      "title": {
                        "type": "string",
                        "example": "在開始之前"
                      },
                      "totalTime": {
                        "type": "number",
                        "example": 3600
                      },
                      "totalNumber": {
                        "type": "number",
                        "example": 5
                      },
                      "subchapters": {
                        "type": "array",
                        "items": {
                          "type": "object",
                          "properties": {
                            "_id": {
                              "type": "string",
                              "example": "6459b6cdaea0942f035f2e37-BB002"
                            },
                            "sequence": {
                              "type": "number",
                              "example": 2
                            },
                            "title": {
                              "type": "string",
                              "example": "環境探索引導"
                            },
                            "content": {},
                            "fileName": {
                              "type": "string",
                              "example": "https://example.com/videos/promo_video.mp4"
                            },
                            "fileType": {
                              "type": "number",
                              "example": 0
                            },
                            "time": {
                              "type": "number",
                              "example": 600
                            }
                          }
                        }
                      }
                    }
                  }
                }
              }
            }
          }
        ],
        "responses": {
          "200": {
            "description": "成功",
            "schema": {
              "type": "object",
              "properties": {
                "statusCode": {
                  "type": "number",
                  "example": 200
                },
                "isSuccess": {
                  "type": "boolean",
                  "example": true
                },
                "message": {
                  "type": "string",
                  "example": "Success"
                }
              },
              "xml": {
                "name": "main"
              }
            }
          },
          "400": {
            "description": "錯誤的請求",
            "schema": {
              "type": "object",
              "properties": {
                "statusCode": {
                  "type": "number",
                  "example": 400
                },
                "isSuccess": {
                  "type": "boolean",
                  "example": false
                },
                "message": {
                  "type": "string",
                  "example": "Failure"
                }
              },
              "xml": {
                "name": "main"
              }
            }
          },
          "500": {
            "description": "伺服器發生錯誤",
            "schema": {
              "type": "object",
              "properties": {
                "statusCode": {
                  "type": "number",
                  "example": 500
                },
                "isSuccess": {
                  "type": "boolean",
                  "example": false
                },
                "message": {
                  "type": "string",
                  "example": "System error, please contact the system administrator"
                }
              },
              "xml": {
                "name": "main"
              }
            }
          }
        }
      }
    },
    "/v1/goldFlow/Card": {
      "post": {
        "tags": [
          "GoldFlow - 金流 API"
        ],
        "description": "讀取購物車資料",
        "parameters": [
          {
            "name": "body",
            "description": "資料格式",
            "in": "body",
            "required": true,
            "schema": {
              "type": "object",
              "properties": {
                "courseIds": {
                  "type": "array",
                  "example": [
                    "646e0e6ffa0eac0933c5a776",
                    "646e0e6ffa0eac0933c5a778",
                    "646e0e6ffa0eac0933c5a77e",
                    "646e0e6ffa0eac0933c5a78c",
                    "646e0e6ffa0eac0933c5a79b",
                    "646e0e6ffa0eac0933c5a79c",
                    "646e0e6ffa0eac0933c5a7ad",
                    "646e0e6ffa0eac0933c5a7ae"
                  ],
                  "items": {
                    "type": "string"
                  }
                }
              }
            }
          }
        ],
        "responses": {
          "200": {
            "description": "成功",
            "schema": {
              "type": "object",
              "properties": {
                "statusCode": {
                  "type": "number",
                  "example": 200
                },
                "isSuccess": {
                  "type": "boolean",
                  "example": true
                },
                "message": {
                  "type": "string",
                  "example": "Success"
                },
                "data": {
                  "type": "object",
                  "properties": {
                    "totalPrice": {
                      "type": "number",
                      "example": 28226
                    },
                    "shoppingCart": {
                      "type": "array",
                      "items": {
                        "type": "object",
                        "properties": {
                          "_id": {
                            "type": "string",
                            "example": "646b8121b65fd84dc4ab0af6"
                          },
                          "title": {
                            "type": "string",
                            "example": "高效狗狗訓練方法"
                          },
                          "cover": {
                            "type": "string",
                            "example": "https://thumbs.dreamstime.com/z/dog-golden-retriever-jumping-autumn-leaves-autumnal-sunlight-77861618.jpg"
                          },
                          "level": {
                            "type": "string",
                            "example": "初階課程"
                          },
                          "time": {
                            "type": "number",
                            "example": 496794
                          },
                          "total": {
                            "type": "number",
                            "example": 48
                          },
                          "instructorName": {
                            "type": "string",
                            "example": "zihyin"
                          },
                          "price": {
                            "type": "number",
                            "example": 8155
                          },
                          "discountPrice": {},
                          "isFree": {
                            "type": "boolean",
                            "example": false
                          }
                        }
                      }
                    },
                    "youMightLike": {
                      "type": "array",
                      "items": {
                        "type": "object",
                        "properties": {
                          "_id": {
                            "type": "string",
                            "example": "646b8121b65fd84dc4ab0b5b"
                          },
                          "title": {
                            "type": "string",
                            "example": "兔兔的健康與飼養"
                          },
                          "cover": {
                            "type": "string",
                            "example": "https://thumbs.dreamstime.com/z/dog-cat-11133177.jpg"
                          },
                          "level": {
                            "type": "string",
                            "example": "初階課程"
                          },
                          "time": {
                            "type": "number",
                            "example": 340664
                          },
                          "total": {
                            "type": "number",
                            "example": 23
                          },
                          "instructorName": {
                            "type": "string",
                            "example": "zihyin"
                          },
                          "price": {
                            "type": "number",
                            "example": 7805
                          },
                          "discountPrice": {},
                          "isFree": {
                            "type": "boolean",
                            "example": false
                          }
                        }
                      }
                    }
                  }
                }
              },
              "xml": {
                "name": "main"
              }
            }
          },
          "500": {
            "description": "伺服器發生錯誤",
            "schema": {
              "type": "object",
              "properties": {
                "statusCode": {
                  "type": "number",
                  "example": 500
                },
                "isSuccess": {
                  "type": "boolean",
                  "example": false
                },
                "message": {
                  "type": "string",
                  "example": "System error, please contact the system administrator"
                }
              },
              "xml": {
                "name": "main"
              }
            }
          }
        }
      }
    },
    "/v1/goldFlow/QueryCoupon": {
      "post": {
        "tags": [
          "GoldFlow - 金流 API"
        ],
        "description": "查詢單筆優惠卷",
        "parameters": [
          {
            "name": "body",
            "description": "資料格式",
            "in": "body",
            "required": true,
            "schema": {
              "type": "object",
              "properties": {
                "courseIds": {
                  "type": "array",
                  "example": [
                    "646e0e6ffa0eac0933c5a776",
                    "646e0e6ffa0eac0933c5a778",
                    "646e0e6ffa0eac0933c5a77e",
                    "646e0e6ffa0eac0933c5a78c",
                    "646e0e6ffa0eac0933c5a79b",
                    "646e0e6ffa0eac0933c5a79c",
                    "646e0e6ffa0eac0933c5a7ad",
                    "646e0e6ffa0eac0933c5a7ae"
                  ],
                  "items": {
                    "type": "string"
                  }
                },
                "couponCode": {
                  "type": "string",
                  "example": "ycks7e6q"
                }
              }
            }
          }
        ],
        "responses": {
          "200": {
            "description": "成功",
            "schema": {
              "type": "object",
              "properties": {
                "statusCode": {
                  "type": "number",
                  "example": 200
                },
                "isSuccess": {
                  "type": "boolean",
                  "example": true
                },
                "message": {
                  "type": "string",
                  "example": "Success"
                },
                "data": {
                  "type": "object",
                  "properties": {
                    "price": {
                      "type": "number",
                      "example": 688
                    }
                  }
                }
              },
              "xml": {
                "name": "main"
              }
            }
          },
          "400": {
            "description": "錯誤的請求",
            "schema": {
              "type": "object",
              "properties": {
                "success": {
                  "type": "boolean",
                  "example": false
                },
                "statusCode": {
                  "type": "number",
                  "example": 400
                },
                "message": {
                  "type": "string",
                  "example": "Failure"
                }
              },
              "xml": {
                "name": "main"
              }
            }
          },
          "500": {
            "description": "伺服器發生錯誤",
            "schema": {
              "type": "object",
              "properties": {
                "statusCode": {
                  "type": "number",
                  "example": 500
                },
                "isSuccess": {
                  "type": "boolean",
                  "example": false
                },
                "message": {
                  "type": "string",
                  "example": "System error, please contact the system administrator"
                }
              },
              "xml": {
                "name": "main"
              }
            }
          }
        }
      }
    },
    "/v1/goldFlow/checkOrder": {
      "post": {
        "tags": [
          "GoldFlow - 金流 API"
        ],
        "description": "讀取確認訂單資料",
        "parameters": [
          {
            "name": "body",
            "description": "資料格式",
            "in": "body",
            "required": true,
            "schema": {
              "type": "object",
              "properties": {
                "courseIds": {
                  "type": "array",
                  "example": [
                    "646f7e2f4802a2dbf6b3eb83",
                    "646f7e2f4802a2dbf6b3eb84",
                    "646f7e2f4802a2dbf6b3eb85"
                  ],
                  "items": {
                    "type": "string"
                  }
                },
                "couponCode": {
                  "type": "string",
                  "example": "ugyV1E8P"
                }
              }
            }
          }
        ],
        "responses": {
          "200": {
            "description": "成功",
            "schema": {
              "type": "object",
              "properties": {
                "statusCode": {
                  "type": "number",
                  "example": 200
                },
                "isSuccess": {
                  "type": "boolean",
                  "example": true
                },
                "message": {
                  "type": "string",
                  "example": "Success"
                },
                "data": {
                  "type": "object",
                  "properties": {
                    "totalPrice": {
                      "type": "number",
                      "example": 7022
                    },
                    "shoppingCart": {
                      "type": "array",
                      "items": {
                        "type": "object",
                        "properties": {
                          "_id": {
                            "type": "string",
                            "example": "646f7e2f4802a2dbf6b3eb85"
                          },
                          "title": {
                            "type": "string",
                            "example": "狗狗訓練實戰指南"
                          },
                          "cover": {
                            "type": "string",
                            "example": "https://thumbs.dreamstime.com/z/dog-jumping-over-pool-water-29720697.jpg"
                          },
                          "level": {
                            "type": "string",
                            "example": "所有級別"
                          },
                          "time": {
                            "type": "number",
                            "example": 52.8
                          },
                          "total": {
                            "type": "number",
                            "example": 87
                          },
                          "instructorName": {
                            "type": "string",
                            "example": "RUBYTEST"
                          },
                          "price": {
                            "type": "number",
                            "example": 1288
                          },
                          "discountPrice": {},
                          "isFree": {
                            "type": "boolean",
                            "example": false
                          }
                        }
                      }
                    },
                    "discountedPrice": {
                      "type": "number",
                      "example": 6210
                    },
                    "platformCoupons": {
                      "type": "object",
                      "properties": {
                        "couponPrice": {
                          "type": "number",
                          "example": 812
                        }
                      }
                    }
                  }
                }
              },
              "xml": {
                "name": "main"
              }
            }
          },
          "400": {
            "description": "請求錯誤",
            "schema": {
              "type": "object",
              "properties": {
                "statusCode": {
                  "type": "number",
                  "example": 400
                },
                "isSuccess": {
                  "type": "boolean",
                  "example": false
                },
                "message": {
                  "type": "string",
                  "example": "Bad Request"
                }
              },
              "xml": {
                "name": "main"
              }
            }
          },
          "500": {
            "description": "伺服器發生錯誤",
            "schema": {
              "type": "object",
              "properties": {
                "statusCode": {
                  "type": "number",
                  "example": 500
                },
                "isSuccess": {
                  "type": "boolean",
                  "example": false
                },
                "message": {
                  "type": "string",
                  "example": "System error, please contact the system administrator"
                }
              },
              "xml": {
                "name": "main"
              }
            }
          }
        }
      }
    },
    "/v1/home": {
      "get": {
        "tags": [
          "Home - 基本 API"
        ],
        "description": "首頁",
        "parameters": [],
        "responses": {
          "200": {
            "description": "成功",
            "schema": {
              "type": "object",
              "properties": {
                "statusCode": {
                  "type": "number",
                  "example": 200
                },
                "isSuccess": {
                  "type": "boolean",
                  "example": true
                },
                "message": {
                  "type": "string",
                  "example": "Retrieve Failure"
                },
                "data": {
                  "type": "object",
                  "properties": {
                    "carousel": {
                      "type": "array",
                      "items": {
                        "type": "object",
                        "properties": {
                          "_id": {
                            "type": "string",
                            "example": "646f7e2f4802a2dbf6b3eb83"
                          },
                          "title": {
                            "type": "string",
                            "example": "狗狗訓練入門課程"
                          },
                          "cover": {
                            "type": "string",
                            "example": "https://thumbs.dreamstime.com/z/dog-golden-retriever-jumping-autumn-leaves-autumnal-sunlight-77861618.jpg"
                          }
                        }
                      }
                    },
                    "popular": {
                      "type": "array",
                      "items": {
                        "type": "object",
                        "properties": {
                          "tag": {
                            "type": "string",
                            "example": "寵物溝通"
                          },
                          "courses": {
                            "type": "array",
                            "items": {
                              "type": "object",
                              "properties": {
                                "_id": {
                                  "type": "string",
                                  "example": "646f7e2f4802a2dbf6b3ebbd"
                                },
                                "title": {
                                  "type": "string",
                                  "example": "建立與你的寵物更深層的連結"
                                },
                                "cover": {
                                  "type": "string",
                                  "example": "https://thumbs.dreamstime.com/z/cat-dog-love-2025305.jpg"
                                },
                                "instructorName": {
                                  "type": "string",
                                  "example": "Benson"
                                },
                                "price": {
                                  "type": "number",
                                  "example": 3688
                                },
                                "discountPrice": {},
                                "isFree": {
                                  "type": "boolean",
                                  "example": false
                                }
                              }
                            }
                          }
                        }
                      }
                    }
                  }
                }
              },
              "xml": {
                "name": "main"
              }
            }
          },
          "400": {
            "description": "錯誤的請求",
            "schema": {
              "type": "object",
              "properties": {
                "success": {
                  "type": "boolean",
                  "example": false
                },
                "statusCode": {
                  "type": "number",
                  "example": 400
                },
                "message": {
                  "type": "string",
                  "example": "Bad Request"
                }
              },
              "xml": {
                "name": "main"
              }
            }
          },
          "500": {
            "description": "伺服器發生錯誤",
            "schema": {
              "type": "object",
              "properties": {
                "statusCode": {
                  "type": "number",
                  "example": 500
                },
                "isSuccess": {
                  "type": "boolean",
                  "example": false
                },
                "message": {
                  "type": "string",
                  "example": "System error, please contact the system administrator"
                }
              },
              "xml": {
                "name": "main"
              }
            }
          }
        }
      }
    },
    "/": {
      "get": {
        "description": "",
        "parameters": [],
        "responses": {
          "200": {
            "description": "OK"
          },
          "500": {
            "description": "Internal Server Error"
          }
        }
      },
      "post": {
        "description": "",
        "parameters": [],
        "responses": {
          "201": {
            "description": "Created"
          },
          "500": {
            "description": "Internal Server Error"
          }
        }
      }
    },
    "/vime": {
      "get": {
        "description": "",
        "parameters": [],
        "responses": {
          "200": {
            "description": "OK"
          }
        }
      }
    },
    "/{id}": {
      "get": {
        "description": "",
        "parameters": [
          {
            "name": "id",
            "in": "path",
            "required": true,
            "type": "string"
          }
        ],
        "responses": {
          "200": {
            "description": "OK"
          },
          "404": {
            "description": "Not Found"
          },
          "500": {
            "description": "Internal Server Error"
          }
        }
      },
      "put": {
        "description": "",
        "parameters": [
          {
            "name": "id",
            "in": "path",
            "required": true,
            "type": "string"
          }
        ],
        "responses": {
          "200": {
            "description": "OK"
          },
          "201": {
            "description": "Created"
          },
          "500": {
            "description": "Internal Server Error"
          }
        }
      },
      "delete": {
        "description": "",
        "parameters": [
          {
            "name": "id",
            "in": "path",
            "required": true,
            "type": "string"
          }
        ],
        "responses": {
          "204": {
            "description": "No Content"
          },
          "500": {
            "description": "Internal Server Error"
          }
        }
      }
    }
  }
}